[   
    {
        "title": "Delete old files",
        "status": "failed",
        "description": "remove all old files",
        "importance": "3",
        "createdAt": "111122222",
        "lastTriedAt": "111122223",
        "triesCount": 1,
        "doneAt": "null",
        "errors": ["Device is busy"]
    },
    {
        "title": "add old files",
        "status": "fulfilled",
        "description": "add all old files",
        "importance": "2",
        "createdAt": "152222123",
        "lastTriedAt": "152222123",
        "triesCount": 1,
        "doneAt": "null",
        "errors": ["Device is busy", "cant find files"]
    },
    {
        "title": "buy a boat",
        "status": "failed",
        "description": "I should buy a boat",
        "importance": "2",
        "createdAt": "152333123",
        "lastTriedAt": "152332123",
        "triesCount": 1,
        "doneAt": "null",
        "errors": ["Device is busy", "cant find boats"]
    },
    {
        "title": "sell a boat",
        "status": "failed",
        "description": "I should sell my boat",
        "importance": "1",
        "createdAt": "152333123",
        "lastTriedAt": "152332123",
        "triesCount": 3,
        "doneAt": "null",
        "errors": ["Device is busy", "cant find buyers"]
    }
]